mcp_server_baidu_maps/__init__.py
mcp_server_baidu_maps/__main__.py
mcp_server_baidu_maps/map.py
nipanbo_mcp_server_baidu_maps-0.1.2.dist-info/licenses/LICENSE
nipanbo_mcp_server_baidu_maps-0.1.2.dist-info/METADATA
nipanbo_mcp_server_baidu_maps-0.1.2.dist-info/WHEEL
nipanbo_mcp_server_baidu_maps-0.1.2.dist-info/entry_points.txt
nipanbo_mcp_server_baidu_maps-0.1.2.dist-info/top_level.txt
nipanbo_mcp_server_baidu_maps-0.1.2.dist-info/RECORD
