Metadata-Version: 2.4
Name: nipanbo-mcp-server-baidu-maps
Version: 0.1.2
Summary: MCP Server Baidu Maps
Author: baidu-maps
Maintainer-email: Pineapple274 <yuyangyang3838@gmail.com>
License: MIT
Keywords: http,mcp,map,baidu
Requires-Python: >=3.10
License-File: LICENSE
Requires-Dist: asyncio>=3.4.3
Requires-Dist: httpx>=0.28.1
Requires-Dist: mcp[cli]>=1.5.0
Dynamic: license-file
